event_listener/__init__.py
event_listener/_version.py
event_listener/exceptions/__init__.py
event_listener/exceptions/exceptions.py
event_listener/listeners/__init__.py
event_listener/listeners/listener.py
event_listener/listeners/listener_async.py
event_listener/utils/__init__.py
event_listener/utils/event_functions.py
event_listener_sharp-0.1.0.dist-info/LICENSE
event_listener_sharp-0.1.0.dist-info/METADATA
event_listener_sharp-0.1.0.dist-info/WHEEL
event_listener_sharp-0.1.0.dist-info/top_level.txt
event_listener_sharp-0.1.0.dist-info/RECORD
