Metadata-Version: 2.1
Name: event-listener-sharp
Version: 0.1.0
Summary: Have c# event handler
Home-page: https://github.com/sacha-renault/event-listener
Author: Sacha Renault
Author-email: 
License: MIT
Platform: UNKNOWN
Classifier: Programming Language :: Python :: 3
Classifier: License :: OSI Approved :: MIT License
Classifier: Operating System :: OS Independent
Requires-Python: >=3.6
License-File: LICENSE
